{
  "title": "Job Advertisement",
  "titleTemplate": "| bluise",
  "welcomeText": "Job purpose: The Principal is responsible for leading, managing, and developing the Presidential School to ensure that it provides the highest standards of education and pastoral care to all students. The principal is also responsible for developing and maintaining effective relationships with all stakeholders, including PIIMA, students, staff, parents, the Board of Governors/Trustees, HR, and the wider community.",
  "logo": "/images/uploads/logo.svg",
  "icon": "/images/uploads/logo.png",
  "loadingColor": "#0b3765",
  "seoDescription": "A quickstart for Nuxt & Netlify CMS",
  "seoMetaImage": ""
}
